dj_weather_show-2.0.0.dist-info/METADATA
dj_weather_show-2.0.0.dist-info/WHEEL
dj_weather_show-2.0.0.dist-info/entry_points.txt
dj_weather_show/__init__.py
dj_weather_show/my.py
dj_weather_show/weather_show.py
dj_weather_show/who.py
dj_weather_show-2.0.0.dist-info/RECORD
