Metadata-Version: 2.1
Name: dj-weather-show
Version: 2.0.0
Summary: only tell you the weather in Dongjak-gu
Author-Email: pysatellite <pysatellite@gmail.com>
License: MIT
Project-URL: Homepage, https://github.com/aaingyunii/hello-aaingyunii_pr
Project-URL: Bug tracker, https://github.com/aaingyunii/hello-aaingyunii_pr/issues
Requires-Python: >=3.8
Requires-Dist: requests>=2.31.0
Requires-Dist: beautifulsoup4>=4.12.2
